<?xml version="1.0" encoding="utf-8"?>
<Task>
 <Property  type="1"  content="128" >
       <Basic id="1086" name="大有不同" level="0" />
       <Mark open="1" share="0" awardui="0" TaskLabel="主线" Charge="0" Nexttask="0" giveUp="0" linklevel="0" repeat="0" typeExtent="0" />
       <Trigger>
           <Target id="0" name="" type="2" />
       </Trigger>
 </Property>
 <Dialog >
    <Desc>  </Desc>
    <Purpose> 0 </Purpose>
    <Fail> 0 </Fail>
    <Finish> 0 </Finish>
 </Dialog>
 <Limit>
    <PreTask  flag="0">
          <Item id="1085" name="力战血魔"/>
     </PreTask>
 </Limit>
<Process>
  <General/>
    <Talk>
      <NPC  id="1076"  name="谢琳">
       <Chat  index="1">
            <PCSpeak>没到瑶池的上下层竟然差别如此之多。</PCSpeak>
            <NPCSpeak>瑶池乃昆仑之顶，仙家福地，自然有所不同。</NPCSpeak>
        </Chat>
       </NPC>
    </Talk>
 </Process>
 <Award>
  <General>
    <Item type="2" value="4230"/>
    <Item type="5" value="60606"/>
   </General>
 </Award>
</Task>
