<?xml version="1.0" encoding="utf-8"?>
<Task>
 <Property  type="1"  content="128" >
       <Basic id="3406" name="悟道威能" level="0" />
       <Mark open="1" share="0" awardui="0" TaskLabel="主线" Charge="0" Nexttask="0" giveUp="0" linklevel="0" repeat="0" typeExtent="0" />
       <Trigger>
           <Target id="0" name="" type="2" />
       </Trigger>
 </Property>
 <Dialog >
    <Desc>  </Desc>
    <Purpose> 0 </Purpose>
    <Fail> 0 </Fail>
    <Finish> 0 </Finish>
 </Dialog>
 <Limit>
    <PreTask  flag="0">
          <Item id="3405" name="血洗魔军"/>
     </PreTask>
 </Limit>
<Process>
  <General/>
    <Talk>
      <NPC  id="1058"  name="齐金蝉">
       <Chat  index="1">
            <PCSpeak>每一次拼尽全力，便自然有收获突悟。</PCSpeak>
            <NPCSpeak>虽然李师姐暂离众仙，但是有我在，护法便不是问题。</NPCSpeak>
        </Chat>
       </NPC>
    </Talk>
 </Process>
 <Award>
  <General>
    <Item type="2" value="4915"/>
    <Item type="5" value="121693"/>
   </General>
 </Award>
</Task>
