<root>
  <update>
    <num001>0</num001>
    <num002>100</num002>
    <num003>190</num003>
    <num004>350</num004>
    <num005>600</num005>
    <num006>960</num006>
    <num007>1450</num007>
    <num008>2090</num008>
    <num009>2900</num009>
    <num010>3900</num010>
    <num011>5836</num011>
    <num012>8140</num012>
    <num013>10844</num013>
    <num014>13980</num014>
    <num015>17580</num015>
    <num016>21676</num016>
    <num017>26300</num017>
    <num018>31484</num018>
    <num019>37260</num019>
    <num020>43660</num020>
    <num021>62182</num021>
    <num022>83478</num022>
    <num023>107812</num023>
    <num024>135460</num024>
    <num025>166710</num025>
    <num026>201862</num026>
    <num027>241228</num027>
    <num028>285132</num028>
    <num029>333910</num029>
    <num030>387910</num030>
    <num031>536865</num031>
    <num032>700705</num032>
    <num033>880390</num033>
    <num034>1076910</num034>
    <num035>1291285</num035>
    <num036>1524565</num036>
    <num037>1777830</num037>
    <num038>2052190</num038>
    <num039>2348785</num039>
    <num040>2668785</num040>
    <num041>3357995</num041>
    <num042>4098875</num042>
    <num043>4893945</num043>
    <num044>5745785</num044>
    <num045>6657035</num045>
    <num046>7630395</num046>
    <num047>8668625</num047>
    <num048>9774545</num048>
    <num049>10951035</num049>
    <num050>12201035</num050>
    <num051>14854055</num051>
    <num052>17666215</num052>
    <num053>20643755</num053>
    <num054>23793035</num054>
    <num055>27120535</num055>
    <num056>30632855</num056>
    <num057>34336715</num057>
    <num058>38238955</num058>
    <num059>42346535</num059>
    <num060>46666535</num060>
    <num061>54610870</num061>
    <num062>62952350</num062>
    <num063>71703995</num063>
    <num064>80879035</num064>
    <num065>90490910</num065>
    <num066>100553270</num066>
    <num067>111079975</num067>
    <num068>122085095</num068>
    <num069>133582910</num069>
    <num070>145587910</num070>
    <num071>168852125</num071>
    <num072>193113245</num072>
    <num073>218399350</num073>
    <num074>244738910</num074>
    <num075>272160785</num075>
    <num076>300694225</num076>
    <num077>330368870</num077>
    <num078>361214750</num078>
    <num079>393262285</num079>
    <num080>426542285</num080>
  </update>
</root>